humai_internal_tools/__init__.py
humai_internal_tools/directus.py
humai_internal_tools/mp.py
humai_internal_tools/utils.py
humai_internal_tools-0.1.5.dist-info/METADATA
humai_internal_tools-0.1.5.dist-info/WHEEL
humai_internal_tools-0.1.5.dist-info/top_level.txt
humai_internal_tools-0.1.5.dist-info/RECORD
