Metadata-Version: 2.1
Name: humai-internal-tools
Version: 0.1.5
Summary: Internal tools for private usage.
Home-page: https://github.com/institutohumai/humai_internal_tools
Author: Humai Dev Team
Author-email: perez.moleroc@gmail.com
License: UNKNOWN
Platform: UNKNOWN
Classifier: Development Status :: 1 - Planning
Classifier: Intended Audience :: Developers
Classifier: License :: OSI Approved :: MIT License
Classifier: Programming Language :: Python :: 3
Classifier: Programming Language :: Python :: 3.7
Classifier: Programming Language :: Python :: 3.8
Classifier: Programming Language :: Python :: 3.9
Classifier: Programming Language :: Python :: 3.10
Requires-Dist: mercadopago
Requires-Dist: pydantic
Requires-Dist: python-dotenv
Requires-Dist: requests
Requires-Dist: unidecode
